[
  {
    "id": 1,
    "year": 2012,
    "make": "audi",
    "model": "x3",
    "kms": "20000 km",
    "transmission": "petrol",
    "exteriorcolor": "red",
    "fuel": "petrol",
    "price": 1900800,
    "image": "https://cdn.bigboytoyz.com/new-version/products/lamborghini-huracan-lp-610-4--431-2.jpg"
  },
  {
    "id": 2,
    "year": 2013,
    "make": "bmw",
    "model": "x3",
    "kms": "20000 km",
    "transmission": "petrol",
    "exteriorcolor": "red",
    "fuel": "petrol",
    "price": 1890080,
    "image": "https://cdn.bigboytoyz.com/new-version/products/screenshot20230828-191826.jpg"
  },
  {
    "id": 3,
    "year": 2014,
    "make": "audi",
    "model": "x3",
    "kms": "20000 km",
    "transmission": "petrol",
    "exteriorcolor": "red",
    "fuel": "petrol",
    "price": 1780080,
    "image": "https://cdn.bigboytoyz.com/new-version/products/add06879-edit.jpg"
  },
  {
    "id": 4,
    "year": 2015,
    "make": "bmw",
    "model": "x3",
    "kms": "20000 km",
    "transmission": "petrol",
    "exteriorcolor": "red",
    "fuel": "petrol",
    "price": 1670080,
    "image": "https://cdn.bigboytoyz.com/new-version/products/screenshot20230824-205529.jpg"
  },
  {
    "id": 5,
    "year": 2016,
    "make": "audi",
    "model": "x3",
    "kms": "20000 km",
    "transmission": "petrol",
    "exteriorcolor": "red",
    "fuel": "petrol",
    "price": 1560080,
    "image": "https://cdn.bigboytoyz.com/new-version/products/2019landroverrangeroversportblack220.jpeg"
  },
  {
    "id": 6,
    "year": 2017,
    "make": "bmw",
    "model": "x3",
    "kms": "20000 km",
    "transmission": "petrol",
    "exteriorcolor": "red",
    "fuel": "petrol",
    "price": 2190080,
    "image": "https://cdn.bigboytoyz.com/new-version/products/mercedeseqswhite001-1-0251.jpeg"
  },
  {
    "id": 7,
    "year": 2018,
    "make": "bmw",
    "model": "x3",
    "kms": "20000 km",
    "transmission": "petrol",
    "exteriorcolor": "red",
    "fuel": "petrol",
    "price": 3490080,
    "image": "https://cdn.bigboytoyz.com/new-version/products/mercedes-maybach-s680-blue-mumbai-20.jpg"
  },
  {
    "id": 8,
    "year": 2019,
    "make": "audi",
    "model": "x3",
    "kms": "20000 km",
    "transmission": "petrol",
    "exteriorcolor": "red",
    "fuel": "petrol",
    "price": 1990080,
    "image": "https://cdn.bigboytoyz.com/new-version/products/screenshot20230821-193325.jpg"
  },
  {
    "id": 9,
    "year": 2022,
    "make": "bmw",
    "model": "x3",
    "kms": "20000 km",
    "transmission": "petrol",
    "exteriorcolor": "red",
    "fuel": "petrol",
    "price": 2190080,
    "image": "https://cdn.bigboytoyz.com/new-version/products/mercedes-benz-eqs580-blue-mumbai-16.jpg"
  },
  {
    "id": 10,
    "year": 2021,
    "make": "audi",
    "model": "x3",
    "kms": "20000 km",
    "transmission": "petrol",
    "exteriorcolor": "white",
    "fuel": "petrol",
    "price": 9890080,
    "image": "https://cdn.bigboytoyz.com/new-version/products/bmw-i8-blue-2015-2211.jpeg"
  },
  {
    "id": 11,
    "year": 2020,
    "make": "audi",
    "model": "x3",
    "kms": "20000 km",
    "transmission": "petrol",
    "exteriorcolor": "white",
    "fuel": "petrol",
    "price": 1290080,
    "image": "https://cdn.bigboytoyz.com/new-version/products/lexus-es300h-luxury---432-1.jpg"
  },
  {
    "id": 12,
    "year": 2019,
    "make": "audi",
    "model": "x3",
    "kms": "20000 km",
    "transmission": "petrol",
    "exteriorcolor": "white",
    "fuel": "petrol",
    "price": 1190080,
    "image": "https://cdn.bigboytoyz.com/new-version/products/porsche-macan-j-white1.jpg"
  },
  {
    "id": 13,
    "year": 2018,
    "make": "audi",
    "model": "x3",
    "kms": "20000 km",
    "transmission": "petrol",
    "exteriorcolor": "white",
    "fuel": "petrol",
    "price": 1090080,
    "image": "https://cdn.bigboytoyz.com/new-version/products/jaguar-xjl-white-8938.jpg"
  },
  {
    "id": 14,
    "year": 2017,
    "make": "audi",
    "model": "x3",
    "kms": "20000 km",
    "transmission": "petrol",
    "exteriorcolor": "red",
    "fuel": "petrol",
    "price": 120080,
    "image": "https://cdn.bigboytoyz.com/new-version/products/mercedes-benz-s400-blue-mumbai-15-of-29.jpg"
  },
  {
    "id": 15,
    "year": 2016,
    "make": "audi",
    "model": "x3",
    "kms": "20000 km",
    "transmission": "petrol",
    "exteriorcolor": "red",
    "fuel": "petrol",
    "price": 1790080,
    "image": "https://cdn.bigboytoyz.com/new-version/products/-bbt-velar-ts.jpg"
  },
  {
    "id": 16,
    "year": 2015,
    "make": "audi",
    "model": "x3",
    "kms": "20000 km",
    "transmission": "petrol",
    "exteriorcolor": "red",
    "fuel": "petrol",
    "price": 1940080,
    "image": "https://cdn.bigboytoyz.com/new-version/products/bmw-740li-m-sport-1.jpg"
  },
  {
    "id": 17,
    "year": 2014,
    "make": "audi",
    "model": "x3",
    "kms": "20000 km",
    "transmission": "petrol",
    "exteriorcolor": "red",
    "fuel": "petrol",
    "price": 1890080,
    "image": "https://cdn.bigboytoyz.com/new-version/products/whatsapp-image-2023-08-12-at-5.31.34-pm.jpeg"
  },
  {
    "id": 18,
    "year": 2013,
    "make": "audi",
    "model": "x3",
    "kms": "20000 km",
    "transmission": "petrol",
    "exteriorcolor": "red",
    "fuel": "petrol",
    "price": 1690080,
    "image": "https://cdn.bigboytoyz.com/new-version/products/bbt-discovery-tn.jpg"
  },
  {
    "id": 19,
    "year": 2012,
    "make": "audi",
    "model": "x3",
    "kms": "20000 km",
    "transmission": "petrol",
    "exteriorcolor": "red",
    "fuel": "petrol",
    "price": 1590080,
    "image": "https://cdn.bigboytoyz.com/new-version/products/img8992.jpg"
  },
  {
    "id": 20,
    "year": 2012,
    "make": "audi",
    "model": "x3",
    "kms": "20000 km",
    "transmission": "petrol",
    "exteriorcolor": "red",
    "fuel": "petrol",
    "price": 190080,
    "image": "https://cdn.bigboytoyz.com/new-version/assets/images/no-image-3.png"
  }
]
